easy_rag/__init__.py
easy_rag/agent.py
easy_rag/embedding.py
easy_rag/index.py
easy_rag/rag_service.py
easy_rag/retriever.py
easy_rag_llm-1.1.6.dist-info/LICENSE
easy_rag_llm-1.1.6.dist-info/METADATA
easy_rag_llm-1.1.6.dist-info/WHEEL
easy_rag_llm-1.1.6.dist-info/top_level.txt
easy_rag_llm-1.1.6.dist-info/RECORD
