Metadata-Version: 2.2
Name: easy-rag-llm
Version: 1.1.6
Summary: Easily implement RAG workflows with pre-built modules and context expansion.
Home-page: https://github.com/Aiden-Kwak/easy_rag
Author: Aiden-Kwak
Author-email: duckracoon@gist.ac.kr
Project-URL: Bug Reports, https://github.com/Aiden-Kwak/easy_rag/issues
Project-URL: Source, https://github.com/Aiden-Kwak/easy_rag
Keywords: rag llm openai deepseek context-expansion nlp
Classifier: Programming Language :: Python :: 3
Classifier: License :: OSI Approved :: MIT License
Classifier: Operating System :: OS Independent
Classifier: Development Status :: 4 - Beta
Classifier: Intended Audience :: Developers
Classifier: Intended Audience :: Science/Research
Classifier: Topic :: Scientific/Engineering :: Artificial Intelligence
Classifier: Topic :: Text Processing :: General
Requires-Python: >=3.8
License-File: LICENSE
Requires-Dist: faiss-cpu
Requires-Dist: numpy>=1.19.0
Requires-Dist: tqdm>=4.65.0
Requires-Dist: pypdf>=3.7.0
Requires-Dist: openai>=1.0.0
Requires-Dist: requests>=2.28.0
Requires-Dist: python-dotenv>=0.19.0
Dynamic: author
Dynamic: author-email
Dynamic: classifier
Dynamic: description
Dynamic: description-content-type
Dynamic: home-page
Dynamic: keywords
Dynamic: project-url
Dynamic: requires-dist
Dynamic: requires-python
Dynamic: summary
